compute_dense_vectors/__init__.py
compute_dense_vectors/cli.py
compute_dense_vectors-1.0.3.dist-info/AUTHORS
compute_dense_vectors-1.0.3.dist-info/LICENSE
compute_dense_vectors-1.0.3.dist-info/METADATA
compute_dense_vectors-1.0.3.dist-info/WHEEL
compute_dense_vectors-1.0.3.dist-info/entry_points.txt
compute_dense_vectors-1.0.3.dist-info/top_level.txt
compute_dense_vectors-1.0.3.dist-info/RECORD
