Metadata-Version: 2.1
Name: compute-dense-vectors
Version: 1.0.3
Summary: Utility to compute dense vector representation for dataset in the document_tracking_resources format base on dense transformers models.
Home-page: https://gitlab.univ-lr.fr/cross-lingual-event-tracking/datasets/dataset_manipulation_tools/compute_dense_vectors
Author: Guillaume Bernard
Author-email: contact@guillaume-bernard.fr
License: UNKNOWN
Project-URL: Bug Tracker, https://gitlab.univ-lr.fr/cross-lingual-event-tracking/datasets/dataset_manipulation_tools/compute_dense_vectors/-/issues
Platform: UNKNOWN
Classifier: Programming Language :: Python :: 3.9
Classifier: License :: OSI Approved :: GNU General Public License v3 (GPLv3)
Classifier: Operating System :: POSIX :: Linux
Classifier: Topic :: Scientific/Engineering :: Artificial Intelligence
Classifier: Intended Audience :: Science/Research
Requires-Python: >=3.9
License-File: LICENSE
License-File: AUTHORS
Requires-Dist: document-tracking-resources (~=1.0.0)
Requires-Dist: pandas (~=1.3.5)
Requires-Dist: sentence-transformers (~=2.1.0)
Requires-Dist: tqdm (~=4.62.3)
